setup.py
saylani_46165/__init__.py
saylani_46165/saylani.py
saylani_46165.egg-info/PKG-INFO
saylani_46165.egg-info/SOURCES.txt
saylani_46165.egg-info/dependency_links.txt
saylani_46165.egg-info/not-zip-safe
saylani_46165.egg-info/top_level.txt